autosimulationcraft-0.1.1.dist-info/top_level.txt
autosimulationcraft-0.1.1.dist-info/entry_points.txt
autosimulationcraft-0.1.1.dist-info/RECORD
autosimulationcraft-0.1.1.dist-info/metadata.json
autosimulationcraft-0.1.1.dist-info/METADATA
autosimulationcraft-0.1.1.dist-info/DESCRIPTION.rst
autosimulationcraft-0.1.1.dist-info/WHEEL
autosimulationcraft/autosimulationcraft.py
autosimulationcraft/version.py
autosimulationcraft/runner.py
autosimulationcraft/config.py
autosimulationcraft/__init__.py
autosimulationcraft/tests/test_runner.py
autosimulationcraft/tests/fixtures.py
autosimulationcraft/tests/data_fixtures.py
autosimulationcraft/tests/test_autosimulationcraft.py
autosimulationcraft/tests/__init__.py
autosimulationcraft/tests/test_version.py
