Metadata-Version: 2.0
Name: autosimulationcraft
Version: 0.1.1
Summary: A python script to run SimulationCraft reports for World of Warcraft characters when their gear/stats/level/etc. changes.
Home-page: http://github.com/jantman/AutoSimulationCraft/
Author: Jason Antman
Author-email: jason@jasonantman.com
License: UNKNOWN
Keywords: WoW Warcraft simc SimulationCraft
Platform: UNKNOWN
Classifier: Development Status :: 4 - Beta
Classifier: Environment :: Console
Classifier: Intended Audience :: End Users/Desktop
Classifier: License :: OSI Approved :: GNU General Public License v3 or later (GPLv3+)
Classifier: Natural Language :: English
Classifier: Operating System :: OS Independent
Classifier: Programming Language :: Python
Classifier: Programming Language :: Python :: 2 :: Only
Classifier: Programming Language :: Python :: 2.7
Classifier: Topic :: Games/Entertainment
Requires-Dist: battlenet (>=0.2.6)
Requires-Dist: dictdiffer (>=0.3.0)
